robomotion/__init__.py
robomotion/capabilities.py
robomotion/debug.py
robomotion/decorators.py
robomotion/error.py
robomotion/event.py
robomotion/factory.py
robomotion/health.py
robomotion/health_pb2.py
robomotion/health_pb2_grpc.py
robomotion/icons.py
robomotion/lmo.py
robomotion/message.py
robomotion/node.py
robomotion/oauth.py
robomotion/plugin.py
robomotion/plugin_pb2.py
robomotion/plugin_pb2_grpc.py
robomotion/port.py
robomotion/runner_pb2.py
robomotion/runner_pb2_grpc.py
robomotion/runtime.py
robomotion/setup.py
robomotion/spec.py
robomotion/tool.py
robomotion/utils.py
robomotion/variable.py
robomotion/testing/__init__.py
robomotion/testing/context.py
robomotion/testing/credential.py
robomotion/testing/harness.py
robomotion/testing/quick.py
robomotion-1.11.0.dist-info/METADATA
robomotion-1.11.0.dist-info/WHEEL
robomotion-1.11.0.dist-info/top_level.txt
robomotion-1.11.0.dist-info/RECORD
