Metadata-Version: 2.4
Name: robomotion
Version: 1.11.0
Home-page: https://robomotion.io/
Author: Robomotion IO
Author-email: support@robomotion.io
Project-URL: Bug Reports, https://github.com/robomotionio/python-lib/issues
Project-URL: Dev Docs, https://docs.robomotion.io/
Project-URL: Slack, https://slack.robomotion.io
Project-URL: Forum, https://forum.robomotion.io/
Project-URL: Discord, https://community.robomotion.io/
Requires-Python: >=3.6
Requires-Dist: protobuf==6.30.2
Requires-Dist: grpcio==1.72.0
Requires-Dist: grpcio-tools==1.72.0
Requires-Dist: jsonpath-ng==1.6.1
Requires-Dist: zipp==3.21.0
Dynamic: author
Dynamic: author-email
Dynamic: home-page
Dynamic: project-url
Dynamic: requires-dist
Dynamic: requires-python
